fastapi_openapierrors/__init__.py
fastapi_openapierrors-0.9.0.dist-info/COPYING
fastapi_openapierrors-0.9.0.dist-info/METADATA
fastapi_openapierrors-0.9.0.dist-info/WHEEL
fastapi_openapierrors-0.9.0.dist-info/top_level.txt
fastapi_openapierrors-0.9.0.dist-info/RECORD
