Metadata-Version: 2.1
Name: fastapi-openapierrors
Version: 0.9.0
Summary: Helpers for implementing errors nicely with OpenAPI and FastAPI.
Home-page: https://gitlab.developers.cam.ac.uk/uis/devops/lib/fastapi-openapierrors
Author: University of Cambridge Information Services
Author-email: devops+fastapi-openapierrors@uis.cam.ac.uk
License: MIT
Platform: UNKNOWN
Classifier: Programming Language :: Python :: 3
Classifier: License :: OSI Approved :: MIT License
Classifier: Development Status :: 4 - Beta
Classifier: Intended Audience :: Developers
Classifier: License :: OSI Approved :: MIT License
Classifier: Operating System :: OS Independent
License-File: COPYING
Requires-Dist: fastapi (>=0.68.0)
